[
  {
    "listing_id": "79101150",
    "property_name": "パークホームズ中野中央フォーシーズンコート",
    "title": "◆最上階3面採光角住戸◆ペット飼育可能◆2014年築◆床暖房等設備充実",
    "url": "https://suumo.jp/ms/chuko/tokyo/sc_nakano/nc_79101150/",
    "price_man": 14900.0,
    "area_sqm": 72.5,
    "land_area_sqm": null,
    "layout": "3LDK+S（納戸）",
    "walk_min": 9,
    "built_year": 2014,
    "first_seen_at": "2026-04-18T16:47:14.209834+00:00",
    "address": "東京都中野区中央５",
    "access_text": "ＪＲ中央線「中野」徒歩9分",
    "exact_station_hits": [
      "中野"
    ],
    "nearby_station_hits": [],
    "dishwasher_hits": [
      "食器洗乾燥機"
    ],
    "brightness_hits": [
      "南向き",
      "陽当り良好",
      "採光",
      "眺望良好",
      "通風良好",
      "角住戸"
    ],
    "ceiling_hits": [],
    "feature_tags": [],
    "detail_summary": "◆最上階3面採光角住戸◆ペット飼育可能◆2014年築◆床暖房等設備充実 ～　売主様から当社が直接お預かりしている専任物件です　～ ●最上階3面採光角住戸につき日当たり眺望良好で明るいお部屋 ●ペット飼育可能（飼育細則等あり） ●2014年築、三井不動産レジデンシャル旧分譲マンション ●床暖房等、設備充実してます ●納戸や大型ウォークインクローゼットがあり、収納スペース豊富です ●お部屋のご見学可能です",
    "preview_image_url": "./data/images/mansions/79101150.jpg",
    "criteria_notes": [
      "exact target station match: 中野",
      "size clears ideal threshold at 72.50 sqm",
      "layout: 3LDK+S（納戸）",
      "price is within budget at 14900万円",
      "walk time meets target at 9 min",
      "built in 2014",
      "dishwasher mentioned in listing",
      "brightness/window positives: 南向き, 陽当り良好, 採光, 眺望良好",
      "listing age: 3 days",
      "first seen: 2026-04-18 (5 days ago)"
    ],
    "score": 90.0
  },
  {
    "listing_id": "78836548",
    "property_name": "マストレジデンス世田谷代田",
    "title": "3階部分、南向き！陽当り・通風良好です◎生活に便利な住環境♪",
    "url": "https://suumo.jp/ms/chuko/tokyo/sc_setagaya/nc_78836548/",
    "price_man": 11180.0,
    "area_sqm": 67.93,
    "land_area_sqm": null,
    "layout": "3LDK",
    "walk_min": 7,
    "built_year": 2016,
    "first_seen_at": "2026-04-18T16:47:14.209834+00:00",
    "address": "東京都世田谷区代田３",
    "access_text": "小田急線「梅ヶ丘」徒歩7分",
    "exact_station_hits": [
      "梅ヶ丘"
    ],
    "nearby_station_hits": [],
    "dishwasher_hits": [
      "食器洗乾燥機"
    ],
    "brightness_hits": [
      "南向き",
      "陽当り良好",
      "採光",
      "通風良好"
    ],
    "ceiling_hits": [],
    "feature_tags": [],
    "detail_summary": "3階部分、南向き！ 陽当り・通風良好です◎ 生活に便利な住環境♪ ◇LDに床暖房 ◇全居室収納 ◇インナーバルコニー設計 ◇24時間ゴミ捨て可 ◇宅配ボックス",
    "preview_image_url": "./data/images/mansions/78836548.jpg",
    "criteria_notes": [
      "exact target station match: 梅ヶ丘",
      "size clears hard threshold at 67.93 sqm",
      "layout: 3LDK",
      "price is within budget at 11180万円",
      "walk time meets target at 7 min",
      "built in 2016",
      "dishwasher mentioned in listing",
      "brightness/window positives: 南向き, 陽当り良好, 採光, 通風良好",
      "listing age: 1 days",
      "first seen: 2026-04-18 (5 days ago)"
    ],
    "score": 87.77
  },
  {
    "listing_id": "78929865",
    "property_name": "エスト・グランディールカーロ吉祥寺本町",
    "title": "吉祥寺本町２（吉祥寺駅） 1億1180万円",
    "url": "https://suumo.jp/ms/chuko/tokyo/sc_musashino/nc_78929865/",
    "price_man": 11180.0,
    "area_sqm": 78.31,
    "land_area_sqm": null,
    "layout": "2LDK",
    "walk_min": 6,
    "built_year": 2001,
    "first_seen_at": "2026-04-18T16:47:14.209834+00:00",
    "address": "東京都武蔵野市吉祥寺本町２",
    "access_text": "ＪＲ総武線「吉祥寺」徒歩6分",
    "exact_station_hits": [
      "吉祥寺"
    ],
    "nearby_station_hits": [],
    "dishwasher_hits": [
      "食器洗乾燥機",
      "食洗機"
    ],
    "brightness_hits": [
      "陽当り良好",
      "日当たり良好",
      "眺望良好",
      "通風良好",
      "角住戸"
    ],
    "ceiling_hits": [],
    "feature_tags": [],
    "detail_summary": "「吉祥寺徒歩6分、新規リフォーム×収納充実の快適住まい」 ・JR中央・総武線、京王井の頭線「吉祥寺」駅徒歩6分の好立地。 ・駅近でありながら落ち着いた住環境に位置し、日常の利便性が高い住まいホテルライクな内廊下設計で、角部屋につき日当たり良好。 ・リフォーム済みのため、引渡後すぐに快適な生活が始められる点も魅力 ・共用部分では大規模修繕工事を実施中（2025年12月末完了予定）で、建物全体の安心感や将来的な価値向上にも期待 ・周辺には東急百貨店、ロフト、サンロード商店街、西友など多様な商業施設が揃い、井の頭恩賜公園へも徒歩7分と生活と自然が両立した環境 外観 2LDK、価格1億1180万円、専有面積78.31m",
    "preview_image_url": "./data/images/mansions/78929865.jpg",
    "criteria_notes": [
      "exact target station match: 吉祥寺",
      "size clears ideal threshold at 78.31 sqm",
      "layout: 2LDK",
      "price is within budget at 11180万円",
      "walk time meets target at 6 min",
      "built in 2001",
      "dishwasher mentioned in listing",
      "brightness/window positives: 陽当り良好, 日当たり良好, 眺望良好, 通風良好",
      "listing age: 2 days",
      "first seen: 2026-04-18 (5 days ago)"
    ],
    "score": 85.87
  },
  {
    "listing_id": "79183554",
    "property_name": "オープンレジデンシア吉祥寺本町",
    "title": "吉祥寺本町２（吉祥寺駅） 1億480万円",
    "url": "https://suumo.jp/ms/chuko/tokyo/sc_musashino/nc_79183554/",
    "price_man": 10480.0,
    "area_sqm": 70.74,
    "land_area_sqm": null,
    "layout": "3LDK",
    "walk_min": 8,
    "built_year": 2022,
    "first_seen_at": "2026-04-18T16:47:14.209834+00:00",
    "address": "東京都武蔵野市吉祥寺本町２",
    "access_text": "ＪＲ中央線「吉祥寺」徒歩8分",
    "exact_station_hits": [
      "吉祥寺"
    ],
    "nearby_station_hits": [],
    "dishwasher_hits": [
      "食器洗乾燥機"
    ],
    "brightness_hits": [
      "南向き"
    ],
    "ceiling_hits": [],
    "feature_tags": [],
    "detail_summary": "■「吉祥寺」駅徒歩8分　■2022年6月築 *。.・◇・.。*オープンレジデンシア吉祥寺本町†*。.・◇・.。* ┏┓　【アクセス】 ┗□━━━━━━━━━━━━━━━━━━━━━━━━━━━ ・中央線 「吉祥寺」駅 徒歩8分 ・京王井の頭線 「吉祥寺」駅 徒歩8分 本物件に関する「ご質問」や「現地ご見学希望」等は 野村の仲介＋(PLUS) 吉祥寺営業部",
    "preview_image_url": "./data/images/mansions/79183554.jpg",
    "criteria_notes": [
      "exact target station match: 吉祥寺",
      "size clears ideal threshold at 70.74 sqm",
      "layout: 3LDK",
      "price is within budget at 10480万円",
      "walk time meets target at 8 min",
      "built in 2022",
      "dishwasher mentioned in listing",
      "brightness/window positives: 南向き",
      "listing age: 2 days",
      "first seen: 2026-04-18 (5 days ago)"
    ],
    "score": 84.58
  },
  {
    "listing_id": "79226646",
    "property_name": "パークホームズ中野",
    "title": "■三井のリハウス■南向きのLDKは約18.2帖ペット飼育可能(規約有)",
    "url": "https://suumo.jp/ms/chuko/tokyo/sc_nakano/nc_79226646/",
    "price_man": 14980.0,
    "area_sqm": 66.33,
    "land_area_sqm": null,
    "layout": "2LDK",
    "walk_min": 9,
    "built_year": 2011,
    "first_seen_at": "2026-04-18T16:47:14.209834+00:00",
    "address": "東京都中野区新井２",
    "access_text": "ＪＲ中央線「中野」徒歩9分",
    "exact_station_hits": [
      "中野"
    ],
    "nearby_station_hits": [],
    "dishwasher_hits": [
      "食器洗乾燥機",
      "食洗機"
    ],
    "brightness_hits": [
      "南向き",
      "採光"
    ],
    "ceiling_hits": [],
    "feature_tags": [],
    "detail_summary": "■三井のリハウス■ 南向きのLDKは約18.2帖 ペット飼育可能(規約有) －物件のおすすめポイント－ ▼立地 ・JR中央本線「中野」徒歩9分 他 ▼特徴 ・三井不動産レジデンシャル(株)旧分譲",
    "preview_image_url": "./data/images/mansions/79226646.jpg",
    "criteria_notes": [
      "exact target station match: 中野",
      "size clears hard threshold at 66.33 sqm",
      "layout: 2LDK",
      "price is within budget at 14980万円",
      "walk time meets target at 9 min",
      "built in 2011",
      "dishwasher mentioned in listing",
      "brightness/window positives: 南向き, 採光",
      "listing age: 2 days",
      "first seen: 2026-04-18 (5 days ago)"
    ],
    "score": 75.23
  },
  {
    "listing_id": "78779520",
    "property_name": "オープンレジデンス中野",
    "title": "中野２（中野駅） 1億380万円",
    "url": "https://suumo.jp/ms/chuko/tokyo/sc_nakano/nc_78779520/",
    "price_man": 10380.0,
    "area_sqm": 73.87,
    "land_area_sqm": null,
    "layout": "2LDK",
    "walk_min": 6,
    "built_year": 2013,
    "first_seen_at": "2026-04-18T16:47:14.209834+00:00",
    "address": "東京都中野区中野２",
    "access_text": "ＪＲ総武線「中野」徒歩6分",
    "exact_station_hits": [
      "中野"
    ],
    "nearby_station_hits": [],
    "dishwasher_hits": [
      "食器洗乾燥機",
      "食洗機"
    ],
    "brightness_hits": [
      "陽当り良好",
      "採光",
      "通風良好",
      "角住戸"
    ],
    "ceiling_hits": [],
    "feature_tags": [
      "0120-803-846 FAX",
      "03-5362-3655",
      "080-9584-4601",
      "TEL",
      "携帯電話"
    ],
    "detail_summary": "□1F～3F部分のメゾネットタイプ□西向き角部屋・73.87m2 ◆2013年7月築 ◆複数路線利用可能 『中野』駅より徒歩6分・『新中野』駅より徒歩10分 ◆（株）オープンハウス・ディベロップメント旧分譲 ◆管理は管理会社に全部委託：日本ハウズイング株式会社（巡回） ◆オートロック・モニター付きインターホン ◆宅配ボックス",
    "preview_image_url": "./data/images/mansions/78779520.jpg",
    "criteria_notes": [
      "exact target station match: 中野",
      "size clears ideal threshold at 73.87 sqm",
      "layout: 2LDK",
      "price is within budget at 10380万円",
      "walk time meets target at 6 min",
      "built in 2013",
      "dishwasher mentioned in listing",
      "brightness/window positives: 陽当り良好, 採光, 通風良好, 角住戸",
      "basement / semi-basement indicators present",
      "listing age: 2 days",
      "first seen: 2026-04-18 (5 days ago)"
    ],
    "score": 73.13
  },
  {
    "listing_id": "20258656",
    "property_name": "オープンレジデンス中野桃園町　Ｓ棟",
    "title": "中野３（中野駅） 1億980万円",
    "url": "https://suumo.jp/ms/chuko/tokyo/sc_nakano/nc_20258656/",
    "price_man": 10980.0,
    "area_sqm": 72.68,
    "land_area_sqm": null,
    "layout": "2LDK",
    "walk_min": 7,
    "built_year": 2010,
    "first_seen_at": "2026-04-18T16:47:14.209834+00:00",
    "address": "東京都中野区中野３",
    "access_text": "ＪＲ中央線「中野」徒歩7分",
    "exact_station_hits": [
      "中野"
    ],
    "nearby_station_hits": [],
    "dishwasher_hits": [
      "食器洗乾燥機",
      "食洗機"
    ],
    "brightness_hits": [
      "南向き",
      "陽当り良好",
      "眺望良好",
      "通風良好"
    ],
    "ceiling_hits": [],
    "feature_tags": [],
    "detail_summary": "■三井のリハウス■ 南向きLDKは広々約19.4帖 閑静な住宅街に位置 －物件のおすすめポイント－ ▼立地 ・JR中央本線・中央・総武緩行線・東京メトロ東西線 「中野」駅　徒歩7分 ・東京メトロ丸ノ内線「新中野」駅　徒歩13分",
    "preview_image_url": "./data/images/mansions/20258656.jpg",
    "criteria_notes": [
      "exact target station match: 中野",
      "size clears ideal threshold at 72.68 sqm",
      "layout: 2LDK",
      "price is within budget at 10980万円",
      "walk time meets target at 7 min",
      "built in 2010",
      "dishwasher mentioned in listing",
      "brightness/window positives: 南向き, 陽当り良好, 眺望良好, 通風良好",
      "basement / semi-basement indicators present",
      "listing age: 2 days",
      "first seen: 2026-04-18 (5 days ago)"
    ],
    "score": 71.29
  },
  {
    "listing_id": "20703519",
    "property_name": "オープンレジデンス祐天寺",
    "title": "東横線「祐天寺」駅徒歩5分！戸建然としたテラス付きメゾネット！室内美麗！",
    "url": "https://suumo.jp/ms/chuko/tokyo/sc_meguro/nc_20703519/",
    "price_man": 10180.0,
    "area_sqm": 65.51,
    "land_area_sqm": null,
    "layout": "2LDK",
    "walk_min": 4,
    "built_year": 2024,
    "first_seen_at": "2026-04-22T15:45:58.724357+00:00",
    "address": "東京都目黒区五本木１",
    "access_text": "東急東横線「祐天寺」徒歩4分",
    "exact_station_hits": [
      "祐天寺"
    ],
    "nearby_station_hits": [],
    "dishwasher_hits": [
      "食器洗乾燥機"
    ],
    "brightness_hits": [],
    "ceiling_hits": [],
    "feature_tags": [],
    "detail_summary": "東横線「祐天寺」駅徒歩5分！戸建然としたテラス付きメゾネット！室内美麗！ ※当物件の一部画像を抜粋しています。 ※映像に誤り・問題がある場合は こちら オープンレジデンス祐天寺の外観（南東側から）［2026年4月21日撮影］ LDK13.4帖［2026年4月21日撮影］ 北側洋室5.0帖［2026年4月21日撮影］ オープンレジデンス祐天寺の外観（北東側から）［2026年4月21日撮影］",
    "preview_image_url": "./data/images/mansions/20703519.jpg",
    "criteria_notes": [
      "exact target station match: 祐天寺",
      "size clears hard threshold at 65.51 sqm",
      "layout: 2LDK",
      "price is within budget at 10180万円",
      "walk time meets target at 4 min",
      "built in 2024",
      "dishwasher mentioned in listing",
      "basement / semi-basement indicators present",
      "listing age: 1 days",
      "first seen: 2026-04-22 (1 days ago)"
    ],
    "score": 70.82
  },
  {
    "listing_id": "20688971",
    "property_name": "レジェンド中野ガーデン",
    "title": "〈購入者特典〉弊社から当物件のご成約でアフターサービス最長10年に！",
    "url": "https://suumo.jp/ms/chuko/tokyo/sc_nakano/nc_20688971/",
    "price_man": 13200.0,
    "area_sqm": 70.0,
    "land_area_sqm": null,
    "layout": "3LDK",
    "walk_min": 5,
    "built_year": 1999,
    "first_seen_at": "2026-04-22T15:45:58.724357+00:00",
    "address": "東京都中野区中野３-27-3",
    "access_text": "ＪＲ中央線「中野」徒歩5分",
    "exact_station_hits": [
      "中野"
    ],
    "nearby_station_hits": [],
    "dishwasher_hits": [
      "食器洗乾燥機",
      "食洗機"
    ],
    "brightness_hits": [
      "南向き"
    ],
    "ceiling_hits": [],
    "feature_tags": [],
    "detail_summary": "〈購入者特典〉弊社から当物件のご成約でアフターサービス最長10年に！ ■見学のご希望や、物件についてのご質問は【0120-261-621】までお気軽にお電話くださいませ（当日も見学可） ■当社は、スター・マイカ・ホールディングス（東証プライム上場）のグループ会社です ○令和8年2月16日　リフォーム済み『アフターサービス保証付』 ＊　特典　＊ 給排水設備・水廻りなどのアフターサービス期間を“2年→最長10年”に延長いたします。詳細はお問い合わせください。 ※本特典は、予告なく変更または終了する場合がございます。 ・クロス・CF・フローリング張替",
    "preview_image_url": "./data/images/mansions/20688971.jpg",
    "criteria_notes": [
      "exact target station match: 中野",
      "size clears ideal threshold at 70.00 sqm",
      "layout: 3LDK",
      "price is within budget at 13200万円",
      "walk time meets target at 5 min",
      "older build year: 1999",
      "dishwasher mentioned in listing",
      "brightness/window positives: 南向き",
      "listing age: 3 days",
      "first seen: 2026-04-22 (1 days ago)"
    ],
    "score": 87.27
  },
  {
    "listing_id": "20141592",
    "property_name": "レジェンド中野ガーデン",
    "title": "中野３（中野駅） 1億2300万円",
    "url": "https://suumo.jp/ms/chuko/tokyo/sc_nakano/nc_20141592/",
    "price_man": 12300.0,
    "area_sqm": 75.42,
    "land_area_sqm": null,
    "layout": "3LDK",
    "walk_min": 5,
    "built_year": 1999,
    "first_seen_at": "2026-04-18T16:47:14.209834+00:00",
    "address": "東京都中野区中野３",
    "access_text": "ＪＲ中央線「中野」徒歩5分",
    "exact_station_hits": [
      "中野"
    ],
    "nearby_station_hits": [],
    "dishwasher_hits": [],
    "brightness_hits": [
      "南向き",
      "陽当り良好",
      "日当たり良好",
      "採光",
      "眺望良好",
      "通風良好",
      "角住戸"
    ],
    "ceiling_hits": [],
    "feature_tags": [],
    "detail_summary": "価格を見直し、よりご検討いただきやすい条件に変更いたしました。 現地集合にてご案内可能です。 〇南向き・角部屋・中野駅5分の好立地〇 ■全部屋床暖対応 ■WIC収納、収納数豊富。 ■ペット飼育可（要申請） ■オートロック・管理人（日勤）安心できるセキュリティ対応。 明るい南向き・3方向角部屋のお部屋です。バルコニー2か所。",
    "preview_image_url": "./data/images/mansions/20141592.jpg",
    "criteria_notes": [
      "exact target station match: 中野",
      "size clears ideal threshold at 75.42 sqm",
      "layout: 3LDK",
      "price is within budget at 12300万円",
      "walk time meets target at 5 min",
      "older build year: 1999",
      "dishwasher not explicitly confirmed",
      "brightness/window positives: 南向き, 陽当り良好, 日当たり良好, 採光",
      "listing age: 5 days",
      "first seen: 2026-04-18 (5 days ago)"
    ],
    "score": 80.34
  },
  {
    "listing_id": "20427979",
    "property_name": "オープンレジデンシア中野",
    "title": "■5階部分南西角部屋 ■充実したセキュリティシステム",
    "url": "https://suumo.jp/ms/chuko/tokyo/sc_nakano/nc_20427979/",
    "price_man": 11680.0,
    "area_sqm": 67.5,
    "land_area_sqm": null,
    "layout": "3LDK",
    "walk_min": 12,
    "built_year": 2017,
    "first_seen_at": "2026-04-18T16:47:14.209834+00:00",
    "address": "東京都中野区中野１",
    "access_text": "ＪＲ中央線「中野」徒歩12分",
    "exact_station_hits": [
      "中野"
    ],
    "nearby_station_hits": [],
    "dishwasher_hits": [
      "食器洗乾燥機",
      "食器洗浄乾燥機"
    ],
    "brightness_hits": [
      "南向き",
      "陽当り良好",
      "角住戸"
    ],
    "ceiling_hits": [],
    "feature_tags": [],
    "detail_summary": "■5階部分南西角部屋 ■充実したセキュリティシステム ■ TES温水式床暖房 部屋全体を足元から暖める温水式の床暖房です。 電気式に比べ、立ち上がりが早いなどのメリットがございます。 ■ 二重床・二重天井 衝撃音を軽減し、静かで快適な暮らしを守ります。 ■ピピッとコンロ",
    "preview_image_url": "./data/images/mansions/20427979.jpg",
    "criteria_notes": [
      "exact target station match: 中野",
      "size clears hard threshold at 67.50 sqm",
      "layout: 3LDK",
      "price is within budget at 11680万円",
      "walk time misses target at 12 min",
      "built in 2017",
      "dishwasher mentioned in listing",
      "brightness/window positives: 南向き, 陽当り良好, 角住戸",
      "listing age: 3 days",
      "first seen: 2026-04-18 (5 days ago)"
    ],
    "score": 78.93
  },
  {
    "listing_id": "20315547",
    "property_name": "オープンレジデンシア中野新井テラス",
    "title": "再開発で注目の中野駅徒歩12分♪ペット飼育可！築浅のため、室内大変綺麗です。",
    "url": "https://suumo.jp/ms/chuko/tokyo/sc_nakano/nc_20315547/",
    "price_man": 12080.0,
    "area_sqm": 68.61,
    "land_area_sqm": null,
    "layout": "3LDK",
    "walk_min": 12,
    "built_year": 2023,
    "first_seen_at": "2026-04-18T16:47:14.209834+00:00",
    "address": "東京都中野区新井１",
    "access_text": "ＪＲ中央線「中野」徒歩12分",
    "exact_station_hits": [
      "中野"
    ],
    "nearby_station_hits": [],
    "dishwasher_hits": [
      "食器洗乾燥機"
    ],
    "brightness_hits": [
      "南向き"
    ],
    "ceiling_hits": [],
    "feature_tags": [
      "https:",
      "lifeplan",
      "loan",
      "www.ad-cast.info"
    ],
    "detail_summary": "再開発で注目の中野駅徒歩12分♪ペット飼育可！築浅のため、室内大変綺麗です。 ☆━━━…‥・　物件の特徴　・‥…━━━☆ ◆２０２３年築の築浅美麗マンション♪ ◆ホテルライクな内廊下で、セキュリティ面も良好 ◆2駅4路線が使えるマルチアクセス♪ ◆オートロック連動のTVモニター付インターホン♪ ◆宅配ロッカー完備♪ ◆設備充実のスマートな都市型レジデンス♪",
    "preview_image_url": "./data/images/mansions/20315547.jpg",
    "criteria_notes": [
      "exact target station match: 中野",
      "size clears hard threshold at 68.61 sqm",
      "layout: 3LDK",
      "price is within budget at 12080万円",
      "walk time misses target at 12 min",
      "built in 2023",
      "dishwasher mentioned in listing",
      "brightness/window positives: 南向き",
      "listing age: 24 days",
      "first seen: 2026-04-18 (5 days ago)"
    ],
    "score": 76.77
  },
  {
    "listing_id": "78280842",
    "property_name": "ルジェンテ吉祥寺",
    "title": "3階南西バルコニーの日当たり良好な2LDK！",
    "url": "https://suumo.jp/ms/chuko/tokyo/sc_musashino/nc_78280842/",
    "price_man": 11980.0,
    "area_sqm": 60.65,
    "land_area_sqm": null,
    "layout": "2LDK",
    "walk_min": 4,
    "built_year": 2008,
    "first_seen_at": "2026-04-18T16:47:14.209834+00:00",
    "address": "東京都武蔵野市吉祥寺南町２",
    "access_text": "ＪＲ中央線「吉祥寺」徒歩4分",
    "exact_station_hits": [
      "吉祥寺"
    ],
    "nearby_station_hits": [],
    "dishwasher_hits": [],
    "brightness_hits": [
      "南西向き",
      "陽当り良好",
      "日当たり良好",
      "採光",
      "角住戸"
    ],
    "ceiling_hits": [],
    "feature_tags": [],
    "detail_summary": "3階南西バルコニーの日当たり良好な2LDK！ ■JR中央線、JR中央・総武緩行線、京王井の頭線「吉祥寺」駅徒歩4分の好立地 ■3階南西バルコニーの角住戸につき日当たり良好 ■約3畳の対面キッチンを設えた2面採光の開放的リビング・ダイニング（約10.2畳） ■2面バルコニー（南西側・北西側） ■各居室に収納あり ■宅配ボックスあり ■安心のオートロック",
    "preview_image_url": "./data/images/mansions/78280842.jpg",
    "criteria_notes": [
      "exact target station match: 吉祥寺",
      "size is below target at 60.65 sqm",
      "layout: 2LDK",
      "price is within budget at 11980万円",
      "walk time meets target at 4 min",
      "built in 2008",
      "dishwasher not explicitly confirmed",
      "brightness/window positives: 南西向き, 陽当り良好, 日当たり良好, 採光",
      "listing age: 2 days",
      "first seen: 2026-04-18 (5 days ago)"
    ],
    "score": 68.75
  },
  {
    "listing_id": "20568095",
    "property_name": "ラビ代々木上原　 広々ルーフバルコニー付3LDK",
    "title": "代々木上原5分 ルーフバルコニー付メゾネットタイプ大型3LDK",
    "url": "https://suumo.jp/ms/chuko/tokyo/sc_shibuya/nc_20568095/",
    "price_man": 15800.0,
    "area_sqm": 98.11,
    "land_area_sqm": null,
    "layout": "3LDK",
    "walk_min": 5,
    "built_year": 2002,
    "first_seen_at": "2026-04-18T16:47:14.209834+00:00",
    "address": "東京都渋谷区西原３",
    "access_text": "東京メトロ千代田線「代々木上原」徒歩5分",
    "exact_station_hits": [
      "代々木上原"
    ],
    "nearby_station_hits": [],
    "dishwasher_hits": [
      "食器洗乾燥機"
    ],
    "brightness_hits": [
      "通風良好",
      "角住戸"
    ],
    "ceiling_hits": [],
    "feature_tags": [],
    "detail_summary": "代々木上原5分 ルーフバルコニー付メゾネットタイプ大型3LDK 代々木上原駅徒歩5分の希少立地に、100m 2 近いゆとりある3LDK住戸。戸建感覚でお住まいいただけるメゾネットタイプに加え、開放感のあるルーフバルコニー付き。渋谷区西原アドレスの第一種低層住居専用地域で落ち着いた住環境を確保しながら、新宿・渋谷方面へのアクセスも良好。専有面積98m 2 超でファミリー層にも対応可能な広さと間取り。代々木上原・幡ヶ谷エリアで広さと立地を両立した物件をお探しの方におすすめの一室です。 ※当物件の一部画像を抜粋しています。 代々木上原5分 100m",
    "preview_image_url": "./data/images/mansions/20568095.jpg",
    "criteria_notes": [
      "exact target station match: 代々木上原",
      "size clears ideal threshold at 98.11 sqm",
      "layout: 3LDK",
      "price is outside target budget at 15800万円",
      "walk time meets target at 5 min",
      "built in 2002",
      "dishwasher mentioned in listing",
      "brightness/window positives: 通風良好, 角住戸",
      "basement / semi-basement indicators present",
      "listing age: 2 days",
      "first seen: 2026-04-18 (5 days ago)"
    ],
    "score": 67.27
  },
  {
    "listing_id": "20269787",
    "property_name": "ＴＨＥパームス祐天寺マスタープレイス",
    "title": "■三井のリハウス■眺望良好な5階部分、南西向き住戸WICを2箇所に設置",
    "url": "https://suumo.jp/ms/chuko/tokyo/sc_setagaya/nc_20269787/",
    "price_man": 17980.0,
    "area_sqm": 70.57,
    "land_area_sqm": null,
    "layout": "3LDK",
    "walk_min": 11,
    "built_year": 2018,
    "first_seen_at": "2026-04-18T16:47:14.209834+00:00",
    "address": "東京都世田谷区下馬１",
    "access_text": "東急東横線「祐天寺」徒歩11分",
    "exact_station_hits": [
      "祐天寺"
    ],
    "nearby_station_hits": [],
    "dishwasher_hits": [
      "食器洗乾燥機",
      "食洗機"
    ],
    "brightness_hits": [
      "南西向き",
      "眺望良好"
    ],
    "ceiling_hits": [],
    "feature_tags": [],
    "detail_summary": "■三井のリハウス■ 眺望良好な5階部分、南西向き住戸 WICを2箇所に設置 －物件のおすすめポイント－ ▼特徴 ・食洗機・ディスポーザー付の対面式キッチン ・全居室に収納有 ・24時間ゴミ出し可能",
    "preview_image_url": "./data/images/mansions/20269787.jpg",
    "criteria_notes": [
      "exact target station match: 祐天寺",
      "size clears ideal threshold at 70.57 sqm",
      "layout: 3LDK",
      "price is outside target budget at 17980万円",
      "walk time misses target at 11 min",
      "built in 2018",
      "dishwasher mentioned in listing",
      "brightness/window positives: 南西向き, 眺望良好",
      "listing age: 2 days",
      "first seen: 2026-04-18 (5 days ago)"
    ],
    "score": 67.11
  }
]